{"title":"TMI.FM 뮤직랩스 ─ 카카오톡 채널","url":"https://pf.kakao.com/_nuEns","favicon":"https://pf.kakao.com/favicon.ico","elements":[{"title":"유니버설 뮤직 그룹의 상장이 의미하는 것","contents":"<a class=\"link_item\" href=\"/_nuEns/86947893\"><span class=\"thume_item\" style=\"background-image: url(&quot;//scrap.kakaocdn.net/dn/b5yubE/btrfIYNh9HR/xfxNmaHsBpr33xuGinPut0/700x380.jpg?width=700&amp;height=380&quot;);\"></span><span class=\"info_item\"><span class=\"txt_g\">유니버설 뮤직 그룹의 상장이 의미하는 것</span><em class=\"emph_g\">www.newspim.com</em></span></a>","link":"https://pf.kakao.com/_nuEns/86947893","retrieved":1670999045325}]}